sdhdf/__init__.py
sdhdf/_version.py
sdhdf/exceptions.py
sdhdf/flagging.py
sdhdf/history.py
sdhdf/logger.py
sdhdf/sdhdf.py
sdhdf/tables.py
sdhdf/version.pyi
sdhdf/data/__init__.py
sdhdf/data/rfi/__init__.py
sdhdf/data/rfi/parkes_rfi.csv
sdhdf/data/tests/__init__.py
sdhdf/data/tests/sdhdf_v1.9.3.hdf
sdhdf/data/tests/sdhdf_v2.0.hdf
sdhdf/data/tests/sdhdf_v2.1.hdf
sdhdf/data/tests/sdhdf_v2.2.hdf
sdhdf/data/tests/sdhdf_v3.0.hdf
sdhdf/data/tests/sdhdf_v4.0.hdf
sdhdf/definitions/__init__.py
sdhdf/definitions/sdhdf_def_v2.0.json
sdhdf/definitions/sdhdf_def_v2.1.json
sdhdf/definitions/sdhdf_def_v2.9.json
sdhdf/definitions/sdhdf_def_v3.0.json
sdhdf/definitions/sdhdf_def_v4.0.json
sdhdf-2025.4.2.dist-info/METADATA
sdhdf-2025.4.2.dist-info/WHEEL
sdhdf-2025.4.2.dist-info/licenses/LICENSE
sdhdf-2025.4.2.dist-info/RECORD
