Metadata-Version: 2.4
Name: sdhdf
Version: 2025.4.2
Summary: A collection of tools for interrogating Spectral-Domain Hierarchical Data Format (SDHDF) files
Project-URL: Homepage, https://bitbucket.csiro.au/projects/CPDA/repos/sdhdf_tools/browse
Project-URL: Bug Tracker, https://jira.csiro.au/projects/CPDA/
Author: Lawrence Toomey, George Hobbs, Alec Thomson
License: MIT License
License-File: LICENSE
Classifier: Development Status :: 3 - Alpha
Classifier: Environment :: Web Environment
Classifier: Intended Audience :: Developers
Classifier: Intended Audience :: Science/Research
Classifier: License :: OSI Approved :: MIT License
Classifier: Operating System :: OS Independent
Classifier: Programming Language :: Python
Classifier: Programming Language :: Python :: 3
Classifier: Programming Language :: Python :: 3 :: Only
Classifier: Programming Language :: Python :: 3.10
Classifier: Programming Language :: Python :: 3.11
Classifier: Programming Language :: Python :: 3.12
Classifier: Programming Language :: Python :: 3.13
Classifier: Topic :: Scientific/Engineering
Classifier: Topic :: Scientific/Engineering :: Astronomy
Classifier: Typing :: Typed
Requires-Python: >=3.10
Requires-Dist: astropy>=5
Requires-Dist: dask
Requires-Dist: distributed
Requires-Dist: h5py>=3.7
Requires-Dist: matplotlib>=3.5
Requires-Dist: numpy>=1.21
Requires-Dist: pandas>=1.4
Requires-Dist: tables>=3.7
Requires-Dist: tabulate
Requires-Dist: tqdm
Requires-Dist: xarray>=2022
Provides-Extra: dev
Requires-Dist: furo; extra == 'dev'
Requires-Dist: ipykernel; extra == 'dev'
Requires-Dist: ipython; extra == 'dev'
Requires-Dist: jupyter; extra == 'dev'
Requires-Dist: myst-parser; extra == 'dev'
Requires-Dist: nbconvert>=7.2; extra == 'dev'
Requires-Dist: nbsphinx; extra == 'dev'
Requires-Dist: nox; extra == 'dev'
Requires-Dist: pre-commit; extra == 'dev'
Requires-Dist: pytest-cov>=3; extra == 'dev'
Requires-Dist: pytest>=6; extra == 'dev'
Requires-Dist: ruff>=0.9.9; extra == 'dev'
Requires-Dist: sphinx-argparse; extra == 'dev'
Requires-Dist: sphinx-autoapi>=2; extra == 'dev'
Requires-Dist: sphinx-autodoc-typehints; extra == 'dev'
Requires-Dist: sphinx-mdinclude>=0.5; extra == 'dev'
Requires-Dist: sphinx-rtd-theme>=1.1; extra == 'dev'
Requires-Dist: sphinx>=4.2; extra == 'dev'
